tableserializer/__init__.py
tableserializer/kitchen.py
tableserializer/recipe.py
tableserializer/integrations/__init__.py
tableserializer/integrations/target.py
tableserializer/serializer/__init__.py
tableserializer/serializer/common.py
tableserializer/serializer/metadata.py
tableserializer/serializer/schema.py
tableserializer/serializer/serializer.py
tableserializer/serializer/table.py
tableserializer/table/__init__.py
tableserializer/table/preprocessor.py
tableserializer/table/row_sampler.py
tableserializer/table/table.py
tableserializer/utils/__init__.py
tableserializer/utils/exceptions.py
tableserializer/utils/functions.py
tableserializer-0.1.0.dist-info/METADATA
tableserializer-0.1.0.dist-info/WHEEL
tableserializer-0.1.0.dist-info/top_level.txt
tableserializer-0.1.0.dist-info/RECORD
