Metadata-Version: 2.2
Name: tableserializer
Version: 0.1.0
Summary: Boil your tabular data down to serializations.
Author-email: Daniel Gomm <daniel.gomm@cwi.nl>
Project-URL: Homepage, https://github.com/daniel-gomm/table-serialization-kitchen
Project-URL: Issues, https://github.com/daniel-gomm/table-serialization-kitchen/issues
Classifier: Programming Language :: Python :: 3
Classifier: Operating System :: OS Independent
Requires-Python: >=3.5
Requires-Dist: pandas>=2.2.3
Requires-Dist: scikit-learn~=1.6.1
Provides-Extra: target
Requires-Dist: target_benchmark>=0.1.1; extra == "target"
Requires-Dist: pytei-client>=0.1.0; extra == "target"
